hallgrimJS/ASCIIMathTeXImg.js
hallgrimJS/HallgrimJS user manual.pdf
hallgrimJS/MultipartEncoder.py
hallgrimJS/__init__.py
hallgrimJS/asciiMathConverter.py
hallgrimJS/custom_markdown.py
hallgrimJS/hallgrimJS.py
hallgrimJS/javaScriptMiscTools.py
hallgrimJS/javaScriptTagProcessing.py
hallgrimJS/javaScriptUtils.py
hallgrimJS/messages.py
hallgrimJS/parser.py
hallgrimJS/skulpt-stdlib.js
hallgrimJS/skulpt.min.js
hallgrimJS/tablemaker.py
hallgrimJS/taskPreProcessing.py
hallgrimJS/templates.py
hallgrimJS/uploader.py
hallgrimJS/v86_ext.js
hallgrimJS/vis-network.min.js
hallgrimJS/GraphNodePics/DoubleCircle.png
hallgrimJS/GraphNodePics/DoubleDiamond.png
hallgrimJS/GraphNodePics/SimpleCircle.png
hallgrimJS/GraphNodePics/SimpleDiamond.png
hallgrimJS/IliasXMLCreator/__init__.py
hallgrimJS/IliasXMLCreator/abstract_question.py
hallgrimJS/IliasXMLCreator/free.py
hallgrimJS/IliasXMLCreator/gap.py
hallgrimJS/IliasXMLCreator/javaScript.py
hallgrimJS/IliasXMLCreator/multi.py
hallgrimJS/IliasXMLCreator/order.py
hallgrimJS/IliasXMLCreator/packer.py
hallgrimJS/IliasXMLCreator/single.py
hallgrimJS/IliasXMLCreator/xmlBuildingBlocks.py
hallgrimJS/JSComponents/JSDrawingCanvas.py
hallgrimJS/JSComponents/JSEditor.py
hallgrimJS/JSComponents/JSGraphEditor.py
hallgrimJS/JSComponents/JSVariableTable.py
hallgrimJS/JSComponents/JSVirtualMachine.py
hallgrimJS/JSComponents/__init__.py
hallgrimJS/xsl_yarosh/README
hallgrimJS/xsl_yarosh/cmarkup.xsl
hallgrimJS/xsl_yarosh/entities.xsl
hallgrimJS/xsl_yarosh/glayout.xsl
hallgrimJS/xsl_yarosh/mmltex.xsl
hallgrimJS/xsl_yarosh/scripts.xsl
hallgrimJS/xsl_yarosh/tables.xsl
hallgrimJS/xsl_yarosh/tokens.xsl
hallgrimJS-0.6.7.data/scripts/hallgrimJS
hallgrimJS-0.6.7.dist-info/LICENSE
hallgrimJS-0.6.7.dist-info/METADATA
hallgrimJS-0.6.7.dist-info/WHEEL
hallgrimJS-0.6.7.dist-info/top_level.txt
hallgrimJS-0.6.7.dist-info/RECORD
