Metadata-Version: 2.1
Name: hallgrimJS
Version: 0.6.7
Summary: A script generator for the ILIAS platform
Home-page: https://gitlab.gwdg.de/lukas.mayer/ilias-generator
Author: Jan Maximilian Michal, Lukas Mayer, Toni Ringling
Author-email: t.ringling@gmx.net
License: MIT
Download-URL: https://gitlab.gwdg.de/lukas.mayer/ilias-generator/repository/archive.tar.gz?ref=0.6.7
Platform: UNKNOWN
Requires-Dist: mistune (>=0.7)
Requires-Dist: pygments (>=2)
Requires-Dist: requests (>=2.8)
Requires-Dist: asciitomathml (>=1.0)
Requires-Dist: lxml
Requires-Dist: rjsmin (>=1.1.0)
